ALU.v
module ALU (a, b, alu_control, out);
	
	input [31:0] a, b;
   	input [2:0] alu_control;
  	output reg [31:0] out;
  
  	integer i;
  
	always @(alu_control  or a or b) begin
		  
		case (alu_control)
	
			3'd0: begin
				out = a + b;
			end
      	
			3'd1: begin
				out = a - b;
			end
	
			3'd2: begin
				out = a & b;
			end
	
			3'd3: begin
				out = a | b;
			end
	
			3'd4: begin
				out = a ~| b;
			end
	
			3'd5: begin
				out = a ^ b;
			end

		default : out=32'bX;
		endcase
	end
 
endmodule

ron_alu_test.v
module ALU_tb;

  `define assert(val, exp)\
     #20\
     if (!(exp === val)) begin\
       $display("Assertion failed on line %0d of %s - expected: %0d, received: %0d",\
       `__LINE__, `__FILE__, exp, val);\
       $finish;\
     end

reg [31:0] a, b;
reg [2:0] alu_control;
wire [31:0] out;

ALU u0 (a, b, alu_control, out);

initial begin
  a = 32'd2;
  b = 32'd2;
  alu_control = 3'd0;
  $display("Starting simulation...");

  // testing ADD
  `assert(out, 4);
  a = 5;
  `assert(out, 7);
  b = -4;
  `assert(out, 1);
  a = 4; // will overflow
  `assert(out, 0);

  // testing SUB
  alu_control = 1;
  `assert(out, 8);
  a = 10;
  b = 6;
  `assert(out, 4);
  b = 15;
  `assert(out, -5);
  `assert(out, 4294967291); // that's actually the same number 
  a = 30;
  `assert(out, 15);

  // testing AND
  a = 10;
  alu_control = 2;
  `assert(out, 10);
  a = 0;
  `assert(out, 0);
  a = 31;
  `assert(out, 15);
  b = 0; 
  `assert(out, 0);
  a = 53245;
  b = 71717;
  `assert(out, 2085);

  // testing OR
  alu_control = 3;
  `assert(out, 122877);
  a = 0;
  `assert(out, 71717);
  b = 0;
  `assert(out, 0);
  a = 32;
  `assert(out, 32);
  
  // testing NOR
  alu_control = 4;
  `assert(out, -33);
  a = 1;
  b = 0;
  `assert(out, -2);
  a = 0;
  `assert(out, -1);
  b = 1;
  `assert(out, -2);
  a = 32'hFFFFFFFF;
  `assert(out, 0);
  a = -1;
  `assert(out, 0);
  b = 50;
  `assert(out, 0);

  // testing XOR
  a = 10;
  b = 15;
  alu_control = 5;
  `assert(out, 5);
  a = 0;
  `assert(out, 15);
  b = 3;
  `assert(out, 3);
  b = 0;
  `assert(out, 0);
  a = 8;
  `assert(out, 8);
  b = 1;
  `assert(out, 9);
  a = 9;
  `assert(out, 8);
  b = -1;
  `assert(out, -10); 
  a = -1;
  `assert(out, 0);
  a = 50;
  b = 50;
  `assert(out, 0);
  b = 51;
  `assert(out, 1);

  // testing invalud alu_control
  alu_control = 6;
  `assert(out, {32{1'bx}});
  a = 4;
  `assert(out, {32{1'bx}});
  b = 2;
  `assert(out, {32{1'bx}});
  a = 3;
  b = 5;
  `assert(out, {32{1'bx}});
  alu_control = 7;
  `assert(out, {32{1'bx}});
  a = 4;
  `assert(out, {32{1'bx}});
  b = 2;
  `assert(out, {32{1'bx}});
  a = 3;
  b = 5;
  `assert(out, {32{1'bx}});

  $display("All tests passed! Good job!");

  $display("Done...");
  $finish;
end

initial begin
   //$monitor("At time %t, control = %0d, out = %0d", $time, alu_control, out);
   $dumpfile("ALU_test.vcd");
	 $dumpvars(0, ALU_tb);
end


endmodule // test

ALU_test.vcd
$date
	Wed Nov  7 17:08:43 2018
$end
$version
	Icarus Verilog
$end
$timescale
	1s
$end
$scope module ALU_tb $end
$var wire 32 ! out [31:0] $end
$var reg 32 " a [31:0] $end
$var reg 3 # alu_control [2:0] $end
$var reg 32 $ b [31:0] $end
$scope module u0 $end
$var wire 32 % a [31:0] $end
$var wire 3 & alu_control [2:0] $end
$var wire 32 ' b [31:0] $end
$var reg 32 ( out [31:0] $end
$upscope $end
$upscope $end
$enddefinitions $end
#0
$dumpvars
b100 (
b10 '
b0 &
b10 %
b10 $
b0 #
b10 "
b100 !
$end
#20
b111 !
b111 (
b101 "
b101 %
#40
b1 !
b1 (
b11111111111111111111111111111100 $
b11111111111111111111111111111100 '
#60
b0 !
b0 (
b100 "
b100 %
#80
b1000 !
b1000 (
b1 #
b1 &
#100
b100 !
b100 (
b110 $
b110 '
b1010 "
b1010 %
#120
b11111111111111111111111111111011 !
b11111111111111111111111111111011 (
b1111 $
b1111 '
#160
b1111 !
b1111 (
b11110 "
b11110 %
#180
b1010 !
b1010 (
b10 #
b10 &
b1010 "
b1010 %
#200
b0 !
b0 (
b0 "
b0 %
#220
b1111 !
b1111 (
b11111 "
b11111 %
#240
b0 !
b0 (
b0 $
b0 '
#260
b100000100101 !
b100000100101 (
b10001100000100101 $
b10001100000100101 '
b1100111111111101 "
b1100111111111101 %
#280
b11101111111111101 !
b11101111111111101 (
b11 #
b11 &
#300
b10001100000100101 !
b10001100000100101 (
b0 "
b0 %
#320
b0 !
b0 (
b0 $
b0 '
#340
b100000 !
b100000 (
b100000 "
b100000 %
#360
b11111111111111111111111111011111 !
b11111111111111111111111111011111 (
b100 #
b100 &
#380
b11111111111111111111111111111110 !
b11111111111111111111111111111110 (
b1 "
b1 %
#400
b11111111111111111111111111111111 !
b11111111111111111111111111111111 (
b0 "
b0 %
#420
b11111111111111111111111111111110 !
b11111111111111111111111111111110 (
b1 $
b1 '
#440
b0 !
b0 (
b11111111111111111111111111111111 "
b11111111111111111111111111111111 %
#480
b110010 $
b110010 '
#500
b101 !
b101 (
b101 #
b101 &
b1111 $
b1111 '
b1010 "
b1010 %
#520
b1111 !
b1111 (
b0 "
b0 %
#540
b11 !
b11 (
b11 $
b11 '
#560
b0 !
b0 (
b0 $
b0 '
#580
b1000 !
b1000 (
b1000 "
b1000 %
#600
b1001 !
b1001 (
b1 $
b1 '
#620
b1000 !
b1000 (
b1001 "
b1001 %
#640
b11111111111111111111111111110110 !
b11111111111111111111111111110110 (
b11111111111111111111111111111111 $
b11111111111111111111111111111111 '
#660
b0 !
b0 (
b11111111111111111111111111111111 "
b11111111111111111111111111111111 %
#680
b110010 $
b110010 '
b110010 "
b110010 %
#700
b1 !
b1 (
b110011 $
b110011 '
#720
bx !
bx (
b110 #
b110 &
#740
b100 "
b100 %
#760
b10 $
b10 '
#780
b101 $
b101 '
b11 "
b11 %
#800
b111 #
b111 &
#820
b100 "
b100 %
#840
b10 $
b10 '
#860
b101 $
b101 '
b11 "
b11 %
