mux3.v
module mux3 #(parameter WIDTH=8) (a, b, c, select, out);
  // select | out
  // 00 | a
  // 01 | b
  // 02 | c
  
	input[1:0] select;
	input [WIDTH-1:0] a,b,c;
	output [WIDTH-1:0] out;
	integer i;

	wire[1:0]  select;
	wire[WIDTH-1:0]a,b,c;
	reg [WIDTH-1:0] out;
	
	always @(select or a or b or c) begin
		case(select)
			2'd0:   out= a;
			2'd1:   out= b;
			2'd2:   out= c;
			default:  out = {WIDTH{1'bX}}; 
		endcase
	end


endmodule

ron_mux_test.v
module mux3_tb;

  `define assert(exp, val)\
     #20\
     if (!(exp === val)) begin\
       $display("Assertion failed on line %0d of %s - expected: %0d, received: %0d",\
       `__LINE__, `__FILE__, exp, val);\
       $finish;\
     end


reg [31:0] a, b, c;
reg [1:0] select;
wire [31:0] out;

  mux3 #(.WIDTH(32)) U0 (
  .a (a),
  .b (b),
  .c (c),
  .select (select),
  .out (out)
  );

initial begin
  a = 32'd1;
  b = 32'd2;
  c = 32'd3;
  select = 2'd0;

  $display("Starting simulation...");
 
  // testing for a input
  #20;
  select = 2'd0;
  `assert(32'd1, out);
  a = 32'd4;
  `assert(32'd4, out);
  a = 32'd0;
  `assert(32'd0, out);

  // testing for b input
  select = 2'd1;
  `assert(32'd2, out);
  b = 32'd5;
  `assert(32'd5, out);
  b = 32'd0; 
  `assert(32'd0, out);

  // testing for c input
  select = 2'd2;
  `assert(32'd3, out);
  c = 32'd6;
  `assert(32'd6, out);
  c = 32'd0; 
  `assert(32'd0, out);

  // testing for select input
  a = 32'd1;
  b = 32'd2;
  c = 32'd3;
  select = 2'd0;
  select = 2'd1;
  `assert(32'd2, out);
  select = 2'd1;
  select = 32'd2;
  `assert(32'd3, out);

  // testing for invalid select = b11
  select = 2'd3;
  `assert({32{1'dx}}, out);

  // big numbers
  a = 32'd4294967295;
  `assert({32{1'dx}}, out); // previous out value
  select = 2'd0; // now changing select to a
  `assert(32'd4294967295, out);

  $display("All tests passed! Good job!");

  $display("Done...");
  $finish;
end

initial begin
  // $monitor("At time %t, value = %0d", $time, select);
   $dumpfile("mux3_test.vcd");
	 $dumpvars(0, mux3_tb);
end

endmodule // test

mux3_test.vcd
$date
	Wed Nov  7 16:55:35 2018
$end
$version
	Icarus Verilog
$end
$timescale
	1s
$end
$scope module mux3_tb $end
$var wire 32 ! out [31:0] $end
$var reg 32 " a [31:0] $end
$var reg 32 # b [31:0] $end
$var reg 32 $ c [31:0] $end
$var reg 2 % select [1:0] $end
$scope module U0 $end
$var wire 32 & a [31:0] $end
$var wire 32 ' b [31:0] $end
$var wire 32 ( c [31:0] $end
$var wire 2 ) select [1:0] $end
$var reg 32 * out [31:0] $end
$upscope $end
$upscope $end
$enddefinitions $end
#0
$dumpvars
b1 *
b0 )
b11 (
b10 '
b1 &
b0 %
b11 $
b10 #
b1 "
b1 !
$end
#40
b100 !
b100 *
b100 "
b100 &
#60
b0 !
b0 *
b0 "
b0 &
#80
b10 !
b10 *
b1 %
b1 )
#100
b101 !
b101 *
b101 #
b101 '
#120
b0 !
b0 *
b0 #
b0 '
#140
b11 !
b11 *
b10 %
b10 )
#160
b110 !
b110 *
b110 $
b110 (
#180
b0 !
b0 *
b0 $
b0 (
#200
b10 !
b10 *
b1 %
b1 )
b11 $
b11 (
b10 #
b10 '
b1 "
b1 &
#220
b11 !
b11 *
b10 %
b10 )
#240
bx !
bx *
b11 %
b11 )
#260
b11111111111111111111111111111111 "
b11111111111111111111111111111111 &
#280
b11111111111111111111111111111111 !
b11111111111111111111111111111111 *
b0 %
b0 )
