simon1.v
module simon1 (clock, reset, in, out);
// in:
// R 00
// G 01
// B 10
// Y 11


   	input wire [1:0] in;
	input wire clock;
	input wire reset;
	output reg [1:0] out;
	
	reg [2:0] state, next_state;
	
	localparam [2:0]
		R = 3'b000,
		G = 3'b001,
		B = 3'b010,
		Y = 3'b011,
		init = 3'b100,
		lose = 3'b101,
		win  = 3'b110;
	
	
	initial begin
		state <= init;
	end


	always @ (posedge clock, posedge reset)	begin
		
		if(reset)
			// change to initial state
			state <= init;

		else
			state <= next_state;
	
	end


	always @ (in, state) begin
		
		case (state)
			init: begin
				next_state <= in;
				out = 2'b00;
			end
			
			R: begin
				if (in == state) begin
					next_state <= win;
					out = 2'b10;
				end
				else begin 
					next_state <= lose;
					out = 2'b01;
				end
			end		

			G: begin
				if (in == state) begin
					next_state <= win;
					out = 2'b10;
				end
				else begin
					next_state <= lose;
					out = 2'b01;
				end
			end

			B: begin
				if (in == state) begin
					next_state <= win;
					out = 2'b10;
				end
				else  begin
					next_state <= lose;
					out = 2'b01;
				end
			end	
			
			Y: begin
				if (in == state) begin
					next_state <= win;
					out = 2'b10;
				end
				else begin 
					next_state <= lose;
					out = 2'b01;
				end
			end
			
			win: begin

			end		

			lose: begin
			end
		endcase

	end

// out:
// X 00
// 0 01
// 1 10
endmodule

ron_test.v
module simon1_tb;

  `define assert(val, exp)\
     #5\
     if (!(exp === val)) begin\
       $display("Assertion failed on line %0d of %s - expected: %0d, received: %0d",\
       `__LINE__, `__FILE__, exp, val);\
       $finish;\
     end

   `define simon_reset;\ // for resetting machine
	  clock = 0;\
	  reset = 1;\
	  clock = 1;\
	  # 1;\
	  reset = 0;\
	  clock = 0;\

reg clock, reset;
reg [1:0] in;
wire [1:0] out;

  simon1 U0 (
  .clock (clock),
  .reset (reset),
  .in    (in),
  .out  (out)
  );


initial begin
  `simon_reset;
  $display("Starting simulation...");

  // testing correct reset
  $display("Testing: Correct reset");
  `assert(out, 0);
  reset = 1;
  `assert(out, 0);
  in = 1;
  `assert(out, 0);
  in = 2;
  `assert(out, 0);
  in = 3;
  `assert(out, 0);
  in = 0;
  `assert(out, 0);
  reset = 0;

  // test R,R to win
  $display("Testing: R->R path");
  in = 0;
  `assert(out, 0);

  clock = 1;
  `assert(out, 2);
  in = 1;
  `assert(out, 1);
  in = 2;
  `assert(out, 1);
  in = 3;
  `assert(out, 1);
  in = 0;
  `assert(out, 2);

  clock = 0;
  `assert(out, 2);
  in = 1;
  `assert(out, 1);
  in = 2;
  `assert(out, 1);
  in = 3;
  `assert(out, 1);
  in = 0;
  `assert(out, 2);

  clock = 1;
  `assert(out, 2);
  clock = 0;

  `assert(out, 2);
  clock = 1;

  `assert(out, 2);

  // test win state
  $display("Testing: Win state");
  in = 1;
  `assert(out, 2);
  clock = 1;
  `assert(out, 2);
  clock = 0;
  in = 2;
  `assert(out, 2);
  clock = 1;
  `assert(out, 2);
  clock = 0;
  in = 3;
  `assert(out, 2);
  clock = 1;
  `assert(out, 2);
  clock = 0;
  in = 0; 
  `assert(out, 2);
  clock = 1;
  `assert(out, 2);
  clock = 0;
  reset = 1;
  `assert(out, 0);

  // test G,G to win
  $display("Testing: G->G path");
  `simon_reset;
  in = 1;
  `assert(out, 0);

  clock = 1;
  `assert(out, 2);
  in = 0;
  `assert(out, 1);
  in = 2;
  `assert(out, 1);
  in = 3;
  `assert(out, 1);
  in = 1;
  `assert(out, 2);

  clock = 0;
  `assert(out, 2);
  in = 0;
  `assert(out, 1);
  in = 2;
  `assert(out, 1);
  in = 3;
  `assert(out, 1);
  in = 1;
  `assert(out, 2);

  clock = 1;
  `assert(out, 2);
  clock = 0;
  in = 0;
  `assert(out, 2);
  in = 2;
  `assert(out, 2);
  in = 3;
  `assert(out, 2);
  in = 1;
  `assert(out, 2);
  `assert(out, 2);
  clock = 1;

  `assert(out, 2);

  // test B, B to win
  $display("Testing: B->B path");
  `simon_reset;
  in = 2;
  `assert(out, 0);

  clock = 1;
  `assert(out, 2);
  in = 0;
  `assert(out, 1);
  in = 1;
  `assert(out, 1);
  in = 3;
  `assert(out, 1);
  in = 2;
  `assert(out, 2);

  clock = 0;
  `assert(out, 2);
  in = 0;
  `assert(out, 1);
  in = 1;
  `assert(out, 1);
  in = 3;
  `assert(out, 1);
  in = 2;
  `assert(out, 2);

  clock = 1;
  `assert(out, 2);
  clock = 0;
  in = 0;
  `assert(out, 2);
  in = 1;
  `assert(out, 2);
  in = 3;
  `assert(out, 2);
  in = 2;
  `assert(out, 2);
  `assert(out, 2);
  clock = 1;

  `assert(out, 2);

  // test Y, Y to win
  $display("Testing: Y->Y path");
  `simon_reset;
  `simon_reset;
  in = 3;
  `assert(out, 0);

  clock = 1;
  `assert(out, 2);
  in = 0;
  `assert(out, 1);
  in = 2;
  `assert(out, 1);
  in = 1;
  `assert(out, 1);
  in = 3;
  `assert(out, 2);

  clock = 0;
  `assert(out, 2);
  in = 0;
  `assert(out, 1);
  in = 2;
  `assert(out, 1);
  in = 1;
  `assert(out, 1);
  in = 3;
  `assert(out, 2);

  clock = 1;
  `assert(out, 2);
  clock = 0;
  in = 0;
  `assert(out, 2);
  in = 2;
  `assert(out, 2);
  in = 1;
  `assert(out, 2);
  in = 3;
  `assert(out, 2);
  `assert(out, 2);
  clock = 1;

  `assert(out, 2);

  // test R, G to lose
  $display("Testing: R->G path");
  `simon_reset;
  in = 0;
  `assert(out, 0);

  clock = 1;
  `assert(out, 2);

  clock = 0;
  in = 1;

  clock = 1;
  `assert(out, 1);
  clock = 0;

  `assert(out, 1);
  clock = 1;

  `assert(out, 1);

  // test lose state
  $display("Testing: Lose state");
  in = 1;
  `assert(out, 1);
  clock = 1;
  `assert(out, 1);
  clock = 0;
  in = 2;
  `assert(out, 1);
  clock = 1;
  `assert(out, 1);
  clock = 0;
  in = 3;
  `assert(out, 1);
  clock = 1;
  `assert(out, 1);
  clock = 0;
  in = 0; 
  `assert(out, 1);
  clock = 1;
  `assert(out, 1);
  clock = 0;
  reset = 1;
  `assert(out, 0);

  // test R, B to lose
  $display("Testing: R->B path");
  `simon_reset;
  in = 0;
  `assert(out, 0);

  clock = 1;
  `assert(out, 2);

  clock = 0;
  in = 2;
  
  clock = 1;
  `assert(out, 1);
  clock = 0;

  `assert(out, 1);
  clock = 1;

  `assert(out, 1);

  // test R, Y to lose
  $display("Testing: R->Y path");
  `simon_reset;
  in = 0;
  `assert(out, 0);

  clock = 1;
  `assert(out, 2);

  clock = 0;
  in = 3;
  
  clock = 1;
  `assert(out, 1);
  clock = 0;

  `assert(out, 1);
  clock = 1;

  `assert(out, 1);

  // test G, R to lose
  $display("Testing: G->R path");
  `simon_reset;
  in = 1;
  `assert(out, 0);

  clock = 1;
  `assert(out, 2);

  clock = 0;
  in = 0;
  
  clock = 1;
  `assert(out, 1);
  clock = 0;

  `assert(out, 1);
  clock = 1;

  `assert(out, 1);

  // test G, B to lose
  $display("Testing: G->B path");
  `simon_reset;
  in = 1;
  `assert(out, 0);

  clock = 1;
  `assert(out, 2);

  clock = 0;
  in = 2;
  
  clock = 1;
  `assert(out, 1);
  clock = 0;

  `assert(out, 1);
  clock = 1;

  `assert(out, 1);

  // test G, Y to lose
  $display("Testing: G->Y path");
  `simon_reset;
  in = 1;
  `assert(out, 0);

  clock = 1;
  `assert(out, 2);

  clock = 0;
  in = 3;
  
  clock = 1;
  `assert(out, 1);
  clock = 0;

  `assert(out, 1);
  clock = 1;

  `assert(out, 1);

  // test B, R to lose
  $display("Testing: B->R path");
  `simon_reset;
  in = 2;
  `assert(out, 0);

  clock = 1;
  `assert(out, 2);

  clock = 0;
  in = 0;
  
  clock = 1;
  `assert(out, 1);
  clock = 0;

  `assert(out, 1);
  clock = 1;

  `assert(out, 1);

  // test B, G to lose
  $display("Testing: B->G path");
  `simon_reset;
  in = 2;
  `assert(out, 0);

  clock = 1;
  `assert(out, 2);

  clock = 0;
  in = 1;
  
  clock = 1;
  `assert(out, 1);
  clock = 0;

  `assert(out, 1);
  clock = 1;

  `assert(out, 1);

  // test B, Y to lose
  $display("Testing: B->Y path");
  `simon_reset;
  in = 2;
  `assert(out, 0);

  clock = 1;
  `assert(out, 2);

  clock = 0;
  in = 3;
  
  clock = 1;
  `assert(out, 1);
  clock = 0;

  `assert(out, 1);
  clock = 1;

  `assert(out, 1);

  // test Y, R to lose
  $display("Testing: Y->R path");
  `simon_reset;
  in = 3;
  `assert(out, 0);

  clock = 1;
  `assert(out, 2);

  clock = 0;
  in = 0;
  
  clock = 1;
  `assert(out, 1);
  clock = 0;

  `assert(out, 1);
  clock = 1;

  `assert(out, 1);

  // test Y, G to lose
  $display("Testing: Y->G path");
  `simon_reset;
  in = 3;
  `assert(out, 0);

  clock = 1;
  `assert(out, 2);

  clock = 0;
  in = 1;
  
  clock = 1;
  `assert(out, 1);
  clock = 0;

  `assert(out, 1);
  clock = 1;

  `assert(out, 1);

  // test Y, B to lose
  $display("Testing: Y->B path");
  `simon_reset;
  in = 3;
  `assert(out, 0);

  clock = 1;
  `assert(out, 2);

  clock = 0;
  in = 2;
  
  clock = 1;
  `assert(out, 1);
  clock = 0;

  `assert(out, 1);
  clock = 1;

  `assert(out, 1);

  $display("All tests passed! Good job!");
  $display("Done...");
  $finish;
end

initial begin
   $dumpfile("simon1_test.vcd");
	 $dumpvars(0, simon1_tb);
end

/*always begin
   #10 clock = !clock;
end*/

endmodule

simon1_test.vcd
$date
	Wed Nov  7 16:46:10 2018
$end
$version
	Icarus Verilog
$end
$timescale
	1s
$end
$scope module simon1_tb $end
$var wire 2 ! out [1:0] $end
$var reg 1 " clock $end
$var reg 2 # in [1:0] $end
$var reg 1 $ reset $end
$scope module U0 $end
$var wire 1 " clock $end
$var wire 2 % in [1:0] $end
$var wire 1 $ reset $end
$var reg 3 & next_state [2:0] $end
$var reg 2 ' out [1:0] $end
$var reg 3 ( state [2:0] $end
$upscope $end
$upscope $end
$enddefinitions $end
#0
$dumpvars
b100 (
b0 '
b0xx &
bx %
1$
bx #
1"
b0 !
$end
#1
0"
0$
#6
1$
#11
b1 &
b1 #
b1 %
#16
b10 &
b10 #
b10 %
#21
b11 &
b11 #
b11 %
#26
b0 &
b0 #
b0 %
#31
0$
#36
b110 &
b10 !
b10 '
b0 (
1"
#41
b101 &
b1 !
b1 '
b1 #
b1 %
#46
b10 #
b10 %
#51
b11 #
b11 %
#56
b110 &
b10 !
b10 '
b0 #
b0 %
#61
0"
#66
b101 &
b1 !
b1 '
b1 #
b1 %
#71
b10 #
b10 %
#76
b11 #
b11 %
#81
b110 &
b10 !
b10 '
b0 #
b0 %
#86
b110 (
1"
#91
0"
#96
1"
#101
b1 #
b1 %
#111
b10 #
b10 %
0"
#116
1"
#121
b11 #
b11 %
0"
#126
1"
#131
b0 #
b0 %
0"
#136
1"
#141
b0 &
b0 !
b0 '
b100 (
1$
0"
#146
1"
#147
b1 &
b1 #
b1 %
0"
0$
#152
b110 &
b10 !
b10 '
b1 (
1"
#157
b101 &
b1 !
b1 '
b0 #
b0 %
#162
b10 #
b10 %
#167
b11 #
b11 %
#172
b110 &
b10 !
b10 '
b1 #
b1 %
#177
0"
#182
b101 &
b1 !
b1 '
b0 #
b0 %
#187
b10 #
b10 %
#192
b11 #
b11 %
#197
b110 &
b10 !
b10 '
b1 #
b1 %
#202
b110 (
1"
#207
b0 #
b0 %
0"
#212
b10 #
b10 %
#217
b11 #
b11 %
#222
b1 #
b1 %
#232
1"
#237
b1 &
b0 !
b0 '
b100 (
1$
1"
#238
b10 &
b10 #
b10 %
0"
0$
#243
b110 &
b10 !
b10 '
b10 (
1"
#248
b101 &
b1 !
b1 '
b0 #
b0 %
#253
b1 #
b1 %
#258
b11 #
b11 %
#263
b110 &
b10 !
b10 '
b10 #
b10 %
#268
0"
#273
b101 &
b1 !
b1 '
b0 #
b0 %
#278
b1 #
b1 %
#283
b11 #
b11 %
#288
b110 &
b10 !
b10 '
b10 #
b10 %
#293
b110 (
1"
#298
b0 #
b0 %
0"
#303
b1 #
b1 %
#308
b11 #
b11 %
#313
b10 #
b10 %
#323
1"
#328
b10 &
b0 !
b0 '
b100 (
1$
1"
#329
1"
1$
#330
b11 &
b11 #
b11 %
0"
0$
#335
b110 &
b10 !
b10 '
b11 (
1"
#340
b101 &
b1 !
b1 '
b0 #
b0 %
#345
b10 #
b10 %
#350
b1 #
b1 %
#355
b110 &
b10 !
b10 '
b11 #
b11 %
#360
0"
#365
b101 &
b1 !
b1 '
b0 #
b0 %
#370
b10 #
b10 %
#375
b1 #
b1 %
#380
b110 &
b10 !
b10 '
b11 #
b11 %
#385
b110 (
1"
#390
b0 #
b0 %
0"
#395
b10 #
b10 %
#400
b1 #
b1 %
#405
b11 #
b11 %
#415
1"
#420
b11 &
b0 !
b0 '
b100 (
1$
1"
#421
b0 &
b0 #
b0 %
0"
0$
#426
b110 &
b10 !
b10 '
b0 (
1"
#431
b110 (
b101 &
b1 !
b1 '
b1 #
b1 %
1"
#436
0"
#441
b101 (
1"
#456
b10 #
b10 %
0"
#461
1"
#466
b11 #
b11 %
0"
#471
1"
#476
b0 #
b0 %
0"
#481
1"
#486
b0 &
b0 !
b0 '
b100 (
1$
0"
#491
1"
#492
0"
0$
#497
b110 &
b10 !
b10 '
b0 (
1"
#502
b110 (
b101 &
b1 !
b1 '
b10 #
b10 %
1"
#507
0"
#512
b101 (
1"
#517
b10 &
b0 !
b0 '
b100 (
1$
1"
#518
b0 &
b0 #
b0 %
0"
0$
#523
b110 &
b10 !
b10 '
b0 (
1"
#528
b110 (
b101 &
b1 !
b1 '
b11 #
b11 %
1"
#533
0"
#538
b101 (
1"
#543
b11 &
b0 !
b0 '
b100 (
1$
1"
#544
b1 &
b1 #
b1 %
0"
0$
#549
b110 &
b10 !
b10 '
b1 (
1"
#554
b110 (
b101 &
b1 !
b1 '
b0 #
b0 %
1"
#559
0"
#564
b101 (
1"
#569
b0 &
b0 !
b0 '
b100 (
1$
1"
#570
b1 &
b1 #
b1 %
0"
0$
#575
b110 &
b10 !
b10 '
b1 (
1"
#580
b110 (
b101 &
b1 !
b1 '
b10 #
b10 %
1"
#585
0"
#590
b101 (
1"
#595
b10 &
b0 !
b0 '
b100 (
1$
1"
#596
b1 &
b1 #
b1 %
0"
0$
#601
b110 &
b10 !
b10 '
b1 (
1"
#606
b110 (
b101 &
b1 !
b1 '
b11 #
b11 %
1"
#611
0"
#616
b101 (
1"
#621
b11 &
b0 !
b0 '
b100 (
1$
1"
#622
b10 &
b10 #
b10 %
0"
0$
#627
b110 &
b10 !
b10 '
b10 (
1"
#632
b110 (
b101 &
b1 !
b1 '
b0 #
b0 %
1"
#637
0"
#642
b101 (
1"
#647
b0 &
b0 !
b0 '
b100 (
1$
1"
#648
b10 &
b10 #
b10 %
0"
0$
#653
b110 &
b10 !
b10 '
b10 (
1"
#658
b110 (
b101 &
b1 !
b1 '
b1 #
b1 %
1"
#663
0"
#668
b101 (
1"
#673
b1 &
b0 !
b0 '
b100 (
1$
1"
#674
b10 &
b10 #
b10 %
0"
0$
#679
b110 &
b10 !
b10 '
b10 (
1"
#684
b110 (
b101 &
b1 !
b1 '
b11 #
b11 %
1"
#689
0"
#694
b101 (
1"
#699
b11 &
b0 !
b0 '
b100 (
1$
1"
#700
0"
0$
#705
b110 &
b10 !
b10 '
b11 (
1"
#710
b110 (
b101 &
b1 !
b1 '
b0 #
b0 %
1"
#715
0"
#720
b101 (
1"
#725
b0 &
b0 !
b0 '
b100 (
1$
1"
#726
b11 &
b11 #
b11 %
0"
0$
#731
b110 &
b10 !
b10 '
b11 (
1"
#736
b110 (
b101 &
b1 !
b1 '
b1 #
b1 %
1"
#741
0"
#746
b101 (
1"
#751
b1 &
b0 !
b0 '
b100 (
1$
1"
#752
b11 &
b11 #
b11 %
0"
0$
#757
b110 &
b10 !
b10 '
b11 (
1"
#762
b110 (
b101 &
b1 !
b1 '
b10 #
b10 %
1"
#767
0"
#772
b101 (
1"
